nestedcontext/__init__.py
nestedcontext/context.py
nestedcontext-0.0.4.dist-info/DESCRIPTION.rst
nestedcontext-0.0.4.dist-info/METADATA
nestedcontext-0.0.4.dist-info/RECORD
nestedcontext-0.0.4.dist-info/WHEEL
nestedcontext-0.0.4.dist-info/metadata.json
nestedcontext-0.0.4.dist-info/top_level.txt
