Metadata-Version: 2.0
Name: nestedcontext
Version: 0.0.4
Summary: Nested context for scoped variables.
Home-page: UNKNOWN
Author: Tony Tung
Author-email: tonytung@merly.org
License: UNKNOWN
Platform: UNKNOWN
